setup.py
pybaldr/__init__.py
pybaldr.egg-info/PKG-INFO
pybaldr.egg-info/SOURCES.txt
pybaldr.egg-info/dependency_links.txt
pybaldr.egg-info/not-zip-safe
pybaldr.egg-info/top_level.txt