Metadata-Version: 1.0
Name: pybaldr
Version: 0.1
Summary: Python library to read the Baldr format from uSwitch
Home-page: http://github.com/coffenbacher/pybaldr
Author: coffenbacher
Author-email: UNKNOWN
License: MIT
Platform: UNKNOWN
